SQLAlchemy_Catalyst/SQLAlchemy_Catalyst.py
SQLAlchemy_Catalyst/__init__.py
SQLAlchemy_Catalyst/version.py
SQLAlchemy_Catalyst-0.1.dist-info/LICENSE
SQLAlchemy_Catalyst-0.1.dist-info/METADATA
SQLAlchemy_Catalyst-0.1.dist-info/WHEEL
SQLAlchemy_Catalyst-0.1.dist-info/top_level.txt
SQLAlchemy_Catalyst-0.1.dist-info/RECORD
