Metadata-Version: 2.1
Name: SQLAlchemy-Catalyst
Version: 0.1
Summary: Collection of methods for base SQLAlchemy classes
Home-page: https://github.com/dcavalcante/SQLAlchemy-Catalyst
Download-URL: https://github.com/dcavalcante/SQLAlchemy-Catalyst/refs/tags/v0.1
Author: Daniel Cavalcante
Author-email: dcavalcante@gmail.com
License: MIT
Keywords: sqlalchemy,sql,mysql,sqlite,postgresql,helpers
Classifier: Development Status :: 3 - Alpha
Classifier: Intended Audience :: Developers
Classifier: License :: OSI Approved :: MIT License
Classifier: Operating System :: OS Independent
Classifier: Programming Language :: Python :: 3
Classifier: Programming Language :: Python :: 3.6
Requires-Python: >=3.6
License-File: LICENSE
Requires-Dist: sqlalchemy
